odoo/addons/hr_holidays_natural_period/README.rst
odoo/addons/hr_holidays_natural_period/__init__.py
odoo/addons/hr_holidays_natural_period/__manifest__.py
odoo/addons/hr_holidays_natural_period/i18n/hr_holidays_natural_period.pot
odoo/addons/hr_holidays_natural_period/models/__init__.py
odoo/addons/hr_holidays_natural_period/models/hr_leave.py
odoo/addons/hr_holidays_natural_period/models/hr_leave_type.py
odoo/addons/hr_holidays_natural_period/models/resource_calendar.py
odoo/addons/hr_holidays_natural_period/readme/CONTRIBUTORS.rst
odoo/addons/hr_holidays_natural_period/readme/DESCRIPTION.rst
odoo/addons/hr_holidays_natural_period/readme/USAGE.rst
odoo/addons/hr_holidays_natural_period/static/description/icon.png
odoo/addons/hr_holidays_natural_period/static/description/index.html
odoo/addons/hr_holidays_natural_period/tests/__init__.py
odoo/addons/hr_holidays_natural_period/tests/test_hr_leave.py
odoo13_addon_hr_holidays_natural_period-13.0.1.0.3.dist-info/METADATA
odoo13_addon_hr_holidays_natural_period-13.0.1.0.3.dist-info/WHEEL
odoo13_addon_hr_holidays_natural_period-13.0.1.0.3.dist-info/top_level.txt
odoo13_addon_hr_holidays_natural_period-13.0.1.0.3.dist-info/RECORD
