Metadata-Version: 2.1
Name: odoo13-addon-hr-holidays-natural-period
Version: 13.0.1.0.3
Summary: Apply natural days in holidays
Home-page: https://github.com/OCA/hr-holidays
Author: Tecnativa, Odoo Community Association (OCA)
Author-email: support@odoo-community.org
License: AGPL-3
Platform: UNKNOWN
Classifier: Programming Language :: Python
Classifier: Framework :: Odoo
Classifier: Framework :: Odoo :: 13.0
Classifier: License :: OSI Approved :: GNU Affero General Public License v3
Requires-Python: >=3.5
Requires-Dist: odoo (<13.1dev,>=13.0a)
